talkpipe_writing_assistant-0.1.3.dist-info/licenses/LICENSE
writing_assistant/__init__.py
writing_assistant/admin_users.py
writing_assistant/create_superuser.py
writing_assistant/app/__init__.py
writing_assistant/app/auth.py
writing_assistant/app/database.py
writing_assistant/app/main.py
writing_assistant/app/models.py
writing_assistant/app/schemas.py
writing_assistant/app/server.py
writing_assistant/app/static/android-chrome-192x192.png
writing_assistant/app/static/android-chrome-512x512.png
writing_assistant/app/static/apple-touch-icon.png
writing_assistant/app/static/favicon-16x16.png
writing_assistant/app/static/favicon-32x32.png
writing_assistant/app/static/favicon.ico
writing_assistant/app/static/logo.png
writing_assistant/app/static/script.js
writing_assistant/app/static/style.css
writing_assistant/app/templates/index.html
writing_assistant/app/templates/login.html
writing_assistant/app/templates/register.html
writing_assistant/core/__init__.py
writing_assistant/core/callbacks.py
writing_assistant/core/definitions.py
talkpipe_writing_assistant-0.1.3.dist-info/METADATA
talkpipe_writing_assistant-0.1.3.dist-info/WHEEL
talkpipe_writing_assistant-0.1.3.dist-info/entry_points.txt
talkpipe_writing_assistant-0.1.3.dist-info/top_level.txt
talkpipe_writing_assistant-0.1.3.dist-info/RECORD
