Metadata-Version: 2.4
Name: talkpipe-writing-assistant
Version: 0.1.3
Summary: AI-powered writing assistant for structured document generation
Author-email: Travis Bauer <tlbauer@sandia.gov>
Maintainer-email: Travis Bauer <tlbauer@sandia.gov>
License-Expression: Apache-2.0
Project-URL: Homepage, https://github.com/sandialabs/talkpipe-writing-assistant
Project-URL: Repository, https://github.com/sandialabs/talkpipe-writing-assistant
Project-URL: Documentation, https://github.com/sandialabs/talkpipe-writing-assistant#readme
Project-URL: Bug Tracker, https://github.com/sandialabs/talkpipe-writing-assistant/issues
Keywords: ai,writing,assistant,document,generation
Classifier: Development Status :: 3 - Alpha
Classifier: Programming Language :: Python :: 3
Classifier: Programming Language :: Python :: 3.11
Classifier: Programming Language :: Python :: 3.12
Classifier: Programming Language :: Python :: 3.13
Classifier: Operating System :: OS Independent
Classifier: Topic :: Text Processing
Classifier: Topic :: Scientific/Engineering :: Artificial Intelligence
Requires-Python: >=3.11.4
License-File: LICENSE
Requires-Dist: talkpipe[all]>=0.11.1a1
Requires-Dist: fastapi[standard]>=0.104.1
Requires-Dist: uvicorn>=0.24.0
Requires-Dist: jinja2>=3.1.2
Requires-Dist: python-multipart>=0.0.6
Requires-Dist: pydantic>=2.0.0
Requires-Dist: fastapi-users[sqlalchemy]>=13.0.0
Requires-Dist: sqlalchemy[asyncio]>=2.0.0
Requires-Dist: aiosqlite>=0.19.0
Requires-Dist: alembic>=1.12.0
Provides-Extra: dev
Requires-Dist: pytest>=7.0.0; extra == "dev"
Requires-Dist: pytest-mock>=3.10.0; extra == "dev"
Requires-Dist: pytest-cov>=4.0.0; extra == "dev"
Requires-Dist: pytest-asyncio>=0.23.0; extra == "dev"
Requires-Dist: httpx>=0.24.0; extra == "dev"
Requires-Dist: black>=23.0.0; extra == "dev"
Requires-Dist: isort>=5.12.0; extra == "dev"
Requires-Dist: flake8>=6.0.0; extra == "dev"
Requires-Dist: mypy>=1.0.0; extra == "dev"
Requires-Dist: bandit>=1.7.0; extra == "dev"
Requires-Dist: safety>=2.3.0; extra == "dev"
Requires-Dist: isort; extra == "dev"
Provides-Extra: test
Requires-Dist: pytest>=7.0.0; extra == "test"
Requires-Dist: pytest-mock>=3.10.0; extra == "test"
Requires-Dist: pytest-cov>=4.0.0; extra == "test"
Requires-Dist: pytest-asyncio>=0.23.0; extra == "test"
Requires-Dist: httpx>=0.24.0; extra == "test"
Provides-Extra: security
Requires-Dist: bandit>=1.7.0; extra == "security"
Requires-Dist: safety>=2.3.0; extra == "security"
Dynamic: license-file
